{
    "name": "BP Score #3a",
    
    "arrivalSynthProperties" : {
        "carrierMultiplier": 1.0,
        "modulatingMultiplier": 3.0,
        "modulationIndex": 3.0,
        "vibratoDepth": 0.1,
        "vibratoRate": 1.3
    },
    "arrivalEnvelope" : {
        "attackDuration": 0.7,
        "decayDuration": 0.3,
        "sustainLevel": 0.3,
        "releaseDuration": 0.1
    },
    "arrivalVelocityRange": [50, 90],
    "arrivalDurationRange": [0.9, 1.1],
    
    "departureSynthProperties" : {
        "carrierMultiplier": 1.0,
        "modulatingMultiplier": 4.0,
        "modulationIndex": 10.0,
        "vibratoDepth": 0.1,
        "vibratoRate": 0.05
    },
    "departureEnvelope" : {
        "attackDuration": 0.3,
        "decayDuration": 0.5,
        "sustainLevel": 0.3,
        "releaseDuration": 0.5
    },
    "departureVelocityRange": [20, 60],
    "departureDurationRange": [1.0, 1.4],
    
    "arrivalNoteNames": ["E3", "C#3", "B2", "D#3", "A2", "F#3"],
    "collision1NoteNames": ["D1", "D2", "A2"],
    "collision2NoteNames": ["E2", "B2", "F#2", "B3"],
    "departureNoteNames": ["B3", "F#3", "D#4", "E4", "A3"],
    
    "collision1AmplitudeRange": [0.1, 0.3],
    "collision2AmplitudeRange": [0.2, 0.6],
    
    "bubbleImageNames": ["sk180313-dot-1", "sk180313-dot-2", "sk180313-dot-3", "sk180313-dot-4", "sk180313-dot-5", "sk180313-dot-6", "sk180313-dot-7"],
    "backgroundImageNames": [""],
    "backgroundDensity": 0.5,
    "screenDivisorRange": [2.0, 2.8],
    "physicsRadiusMultiplier": 0.9,
    "velocityXRange": [-50.0, 50.0],
    "velocityYRange": [-50.0, 50.0],
    
    "tempo": 45.0,
    
    "bubbleCountRange": [3, 15],
    "bubbleAgeRange": [12, 18],
    "containsBubbles": true
}


